sshtmux/__init__.py
sshtmux/__main__.py
sshtmux/cmds/__init__.py
sshtmux/cmds/cmd_group.py
sshtmux/cmds/cmd_host.py
sshtmux/cmds/cmd_identity.py
sshtmux/cmds/cmd_snippets.py
sshtmux/cmds/group/__init__.py
sshtmux/cmds/group/group_create.py
sshtmux/cmds/group/group_delete.py
sshtmux/cmds/group/group_list.py
sshtmux/cmds/group/group_rename.py
sshtmux/cmds/group/group_set.py
sshtmux/cmds/group/group_show.py
sshtmux/cmds/host/__init__.py
sshtmux/cmds/host/host_create.py
sshtmux/cmds/host/host_delete.py
sshtmux/cmds/host/host_list.py
sshtmux/cmds/host/host_rename.py
sshtmux/cmds/host/host_run.py
sshtmux/cmds/host/host_set.py
sshtmux/cmds/host/host_show.py
sshtmux/cmds/identity/identity_create.py
sshtmux/cmds/identity/identity_delete.py
sshtmux/cmds/identity/identity_generate.py
sshtmux/cmds/identity/identity_list.py
sshtmux/cmds/identity/identity_run.py
sshtmux/cmds/identity/identity_update.py
sshtmux/cmds/snippets/snippets_list.py
sshtmux/cmds/snippets/snippets_run.py
sshtmux/core/config.py
sshtmux/exceptions.py
sshtmux/main.py
sshtmux/main_tui.py
sshtmux/services/connections_erros.py
sshtmux/services/identities.py
sshtmux/services/snippets.py
sshtmux/services/tmux.py
sshtmux/sshm/__init__.py
sshtmux/sshm/host_styles/__init__.py
sshtmux/sshm/host_styles/card.py
sshtmux/sshm/host_styles/json.py
sshtmux/sshm/host_styles/panels.py
sshtmux/sshm/host_styles/simple.py
sshtmux/sshm/host_styles/table.py
sshtmux/sshm/host_styles/table2.py
sshtmux/sshm/ssh_config.py
sshtmux/sshm/ssh_graph.py
sshtmux/sshm/ssh_group.py
sshtmux/sshm/ssh_host.py
sshtmux/sshm/ssh_parameters.py
sshtmux/sshm/sshutils.py
sshtmux/version.py
sshtmux-0.2.0.dist-info/LICENSE
sshtmux-0.2.0.dist-info/METADATA
sshtmux-0.2.0.dist-info/WHEEL
sshtmux-0.2.0.dist-info/entry_points.txt
sshtmux-0.2.0.dist-info/RECORD
