Metadata-Version: 2.1
Name: sshtmux
Version: 0.2.0
Summary: Powerful SSH terminal manager
Home-page: https://github.com/scjorge/sshtmux
License: MIT
Keywords: ssh,ssh-manager,sftp,sftp-manager,terminal,command-line,automation,remote-access,networking,devops,secure-shell,tui,cli,cli-tool
Author: Jorge Silva
Author-email: jorgesilva.ti@hotmail.com
Requires-Python: >=3.9,<4.0
Classifier: Development Status :: 3 - Alpha
Classifier: Environment :: Console
Classifier: Environment :: No Input/Output (Daemon)
Classifier: Intended Audience :: Developers
Classifier: Intended Audience :: System Administrators
Classifier: License :: OSI Approved :: MIT License
Classifier: Operating System :: MacOS :: MacOS X
Classifier: Operating System :: Microsoft :: Windows
Classifier: Operating System :: POSIX :: Linux
Classifier: Programming Language :: Python :: 3
Classifier: Programming Language :: Python :: 3.9
Classifier: Programming Language :: Python :: 3.10
Classifier: Programming Language :: Python :: 3.11
Classifier: Programming Language :: Python :: 3.12
Classifier: Topic :: Security
Classifier: Topic :: Security :: Cryptography
Classifier: Topic :: Software Development :: Libraries :: Python Modules
Classifier: Topic :: System :: Networking
Classifier: Topic :: System :: Systems Administration
Classifier: Topic :: Utilities
Requires-Dist: click (>=8.1,<9.0)
Requires-Dist: cryptography (>=43.0.3,<44.0.0)
Requires-Dist: libtmux (>=0.37.0,<0.38.0)
Requires-Dist: pydantic (>=2.9.2,<3.0.0)
Requires-Dist: pydantic-settings (>=2.6.1,<3.0.0)
Requires-Dist: rich (>=13.3,<14.0)
Requires-Dist: textual (>=0.85.1,<0.86.0)
Requires-Dist: toml (>=0.10.2,<0.11.0)
